problems/04_hex_display/hex_display.v
module hex_display(
    input clk,
    input [15:0]data,

    output [3:0]anodes,
    output [6:0]segments
);

/*
*   Problem 3/7:
*   Write logic for dynamic indication here.
*/
//Solve:
reg [1:0]i = 0;

assign anodes = (4'b1 << i);

always @(posedge clk) begin
    i <= i + 2'b1;
end

wire [3:0]b = data[i * 4 +: 4];
hex_to_seg hex_to_seg(.data(b), .segments(segments));

endmodule

module hex_to_seg(
    input [3:0]data,

    output reg [6:0]segments
);

always @(*) begin
    case (data)          /* abcdefg */
        4'h0: segments = 7'b1111110;
        4'h1: segments = 7'b0110000;
        /*
        *   Problem 2/7:
        *   Write logic for missing digits (0x2-0xE) here.
        */
        //Solve:
        4'h2: segments = 7'b1101101;
        4'h3: segments = 7'b1111001;
        4'hA: segments = 7'b1110111;
        4'hC: segments = 7'b1001110;
        4'hF: segments = 7'b1000111;
        4'hE: segments = 7'b1001111;
    endcase
end

endmodule

problems/04_hex_display/clk_div.v
module clk_div #(parameter x = 10)(
  input clk,

  output clk_out
);


reg [x-1:0]cnt = 0;
assign clk_out = cnt[x-1];

always @ (posedge clk) begin
  cnt <= cnt + 1;
end
endmodule

problems/04_hex_display/top.v
module top(
    input CLK,

    output DS_EN1, DS_EN2, DS_EN3, DS_EN4,
    output DS_A, DS_B, DS_C, DS_D, DS_E, DS_F, DS_G
);

wire [15:0]d = 16'hCAFE; /* Data to display */

wire [3:0]anodes;
assign {DS_EN1, DS_EN2, DS_EN3, DS_EN4} = ~anodes;

wire [6:0]segments;
assign {DS_A, DS_B, DS_C, DS_D, DS_E, DS_F, DS_G} = segments;

/*
*   Problem 1/7:
*   Make an instance of clock divider here.
*   Connect CLK to the input.
*/
//Solve:
  clk_div #(.x(16)) div(.clk(CLK),.clk_out(clk2));
/*
*   Problem 4/7:
*   Make an instance of hex display driver (hex_display) here.
*   Connect 'anodes', 'segments', 'data' to corresponding wires in current
*   module.
*/
//Solve:
  hex_display display(.clk(clk2),.data(d),.anodes(anodes),.segments(segments));
endmodule

problems/04_hex_display/testbench.v
`timescale 1 ns / 100 ps

/*
*   Introduction to FPGA and Verilog
*
*   Viktor Prutyanov, 2019
*
*   Testbench for problem set #04
*/

module testbench();

/*
*   Problem 5/7:
*   Create a clock.
*/
//Solve:
reg clk = 1'b0;

always begin
    #1 clk = ~clk;
end

top top(clk, DS_EN1, DS_EN2, DS_EN3, DS_EN4, DS_A, DS_B, DS_C, DS_D, DS_E, DS_F, DS_G);

initial begin
    $dumpvars;
    #100 $finish;
end

endmodule

problems/04_hex_display/dump.vcd
$date
	Mon Nov 11 19:43:10 2019
$end
$version
	Icarus Verilog
$end
$timescale
	100ps
$end
$scope module testbench $end
$var wire 1 ! DS_G $end
$var wire 1 " DS_F $end
$var wire 1 # DS_EN4 $end
$var wire 1 $ DS_EN3 $end
$var wire 1 % DS_EN2 $end
$var wire 1 & DS_EN1 $end
$var wire 1 ' DS_E $end
$var wire 1 ( DS_D $end
$var wire 1 ) DS_C $end
$var wire 1 * DS_B $end
$var wire 1 + DS_A $end
$var reg 1 , clk $end
$scope module top $end
$var wire 1 , CLK $end
$var wire 16 - d [15:0] $end
$var wire 7 . segments [6:0] $end
$var wire 1 / clk2 $end
$var wire 4 0 anodes [3:0] $end
$var wire 1 ! DS_G $end
$var wire 1 " DS_F $end
$var wire 1 # DS_EN4 $end
$var wire 1 $ DS_EN3 $end
$var wire 1 % DS_EN2 $end
$var wire 1 & DS_EN1 $end
$var wire 1 ' DS_E $end
$var wire 1 ( DS_D $end
$var wire 1 ) DS_C $end
$var wire 1 * DS_B $end
$var wire 1 + DS_A $end
$scope module display $end
$var wire 16 1 data [15:0] $end
$var wire 7 2 segments [6:0] $end
$var wire 1 / clk $end
$var wire 4 3 b [3:0] $end
$var wire 4 4 anodes [3:0] $end
$var reg 2 5 i [1:0] $end
$scope module hex_to_seg $end
$var wire 4 6 data [3:0] $end
$var reg 7 7 segments [6:0] $end
$upscope $end
$upscope $end
$scope module div $end
$var wire 1 , clk $end
$var wire 1 / clk_out $end
$var reg 1 8 cnt $end
$upscope $end
$upscope $end
$upscope $end
$enddefinitions $end
#0
$dumpvars
08
b1001111 7
b1110 6
b0 5
b1 4
b1110 3
b1001111 2
b1100101011111110 1
b1 0
0/
b1001111 .
b1100101011111110 -
0,
1+
0*
0)
1(
1'
1&
1%
1$
0#
1"
1!
$end
#10
0$
1#
0(
b1000111 .
b1000111 2
b1000111 7
b10 0
b10 4
b1111 3
b1111 6
b1 5
1/
18
1,
#20
0,
#30
0/
08
1,
#40
0,
#50
0%
1$
1*
1)
b1110111 .
b1110111 2
b1110111 7
b100 0
b100 4
b1010 3
b1010 6
b10 5
1/
18
1,
#60
0,
#70
0/
08
1,
#80
0,
#90
0&
1%
0*
0)
1(
0!
b1001110 .
b1001110 2
b1001110 7
b1000 0
b1000 4
b1100 3
b1100 6
b11 5
1/
18
1,
#100
0,
#110
0/
08
1,
#120
0,
#130
1&
0#
1!
b1001111 .
b1001111 2
b1001111 7
b1 0
b1 4
b1110 3
b1110 6
b0 5
1/
18
1,
#140
0,
#150
0/
08
1,
#160
0,
#170
0$
1#
0(
b1000111 .
b1000111 2
b1000111 7
b10 0
b10 4
b1111 3
b1111 6
b1 5
1/
18
1,
#180
0,
#190
0/
08
1,
#200
0,
#210
0%
1$
1*
1)
b1110111 .
b1110111 2
b1110111 7
b100 0
b100 4
b1010 3
b1010 6
b10 5
1/
18
1,
#220
0,
#230
0/
08
1,
#240
0,
#250
0&
1%
0*
0)
1(
0!
b1001110 .
b1001110 2
b1001110 7
b1000 0
b1000 4
b1100 3
b1100 6
b11 5
1/
18
1,
#260
0,
#270
0/
08
1,
#280
0,
#290
1&
0#
1!
b1001111 .
b1001111 2
b1001111 7
b1 0
b1 4
b1110 3
b1110 6
b0 5
1/
18
1,
#300
0,
#310
0/
08
1,
#320
0,
#330
0$
1#
0(
b1000111 .
b1000111 2
b1000111 7
b10 0
b10 4
b1111 3
b1111 6
b1 5
1/
18
1,
#340
0,
#350
0/
08
1,
#360
0,
#370
0%
1$
1*
1)
b1110111 .
b1110111 2
b1110111 7
b100 0
b100 4
b1010 3
b1010 6
b10 5
1/
18
1,
#380
0,
#390
0/
08
1,
#400
0,
#410
0&
1%
0*
0)
1(
0!
b1001110 .
b1001110 2
b1001110 7
b1000 0
b1000 4
b1100 3
b1100 6
b11 5
1/
18
1,
#420
0,
#430
0/
08
1,
#440
0,
#450
1&
0#
1!
b1001111 .
b1001111 2
b1001111 7
b1 0
b1 4
b1110 3
b1110 6
b0 5
1/
18
1,
#460
0,
#470
0/
08
1,
#480
0,
#490
0$
1#
0(
b1000111 .
b1000111 2
b1000111 7
b10 0
b10 4
b1111 3
b1111 6
b1 5
1/
18
1,
#500
0,
#510
0/
08
1,
#520
0,
#530
0%
1$
1*
1)
b1110111 .
b1110111 2
b1110111 7
b100 0
b100 4
b1010 3
b1010 6
b10 5
1/
18
1,
#540
0,
#550
0/
08
1,
#560
0,
#570
0&
1%
0*
0)
1(
0!
b1001110 .
b1001110 2
b1001110 7
b1000 0
b1000 4
b1100 3
b1100 6
b11 5
1/
18
1,
#580
0,
#590
0/
08
1,
#600
0,
#610
1&
0#
1!
b1001111 .
b1001111 2
b1001111 7
b1 0
b1 4
b1110 3
b1110 6
b0 5
1/
18
1,
#620
0,
#630
0/
08
1,
#640
0,
#650
0$
1#
0(
b1000111 .
b1000111 2
b1000111 7
b10 0
b10 4
b1111 3
b1111 6
b1 5
1/
18
1,
#660
0,
#670
0/
08
1,
#680
0,
#690
0%
1$
1*
1)
b1110111 .
b1110111 2
b1110111 7
b100 0
b100 4
b1010 3
b1010 6
b10 5
1/
18
1,
#700
0,
#710
0/
08
1,
#720
0,
#730
0&
1%
0*
0)
1(
0!
b1001110 .
b1001110 2
b1001110 7
b1000 0
b1000 4
b1100 3
b1100 6
b11 5
1/
18
1,
#740
0,
#750
0/
08
1,
#760
0,
#770
1&
0#
1!
b1001111 .
b1001111 2
b1001111 7
b1 0
b1 4
b1110 3
b1110 6
b0 5
1/
18
1,
#780
0,
#790
0/
08
1,
#800
0,
#810
0$
1#
0(
b1000111 .
b1000111 2
b1000111 7
b10 0
b10 4
b1111 3
b1111 6
b1 5
1/
18
1,
#820
0,
#830
0/
08
1,
#840
0,
#850
0%
1$
1*
1)
b1110111 .
b1110111 2
b1110111 7
b100 0
b100 4
b1010 3
b1010 6
b10 5
1/
18
1,
#860
0,
#870
0/
08
1,
#880
0,
#890
0&
1%
0*
0)
1(
0!
b1001110 .
b1001110 2
b1001110 7
b1000 0
b1000 4
b1100 3
b1100 6
b11 5
1/
18
1,
#900
0,
#910
0/
08
1,
#920
0,
#930
1&
0#
1!
b1001111 .
b1001111 2
b1001111 7
b1 0
b1 4
b1110 3
b1110 6
b0 5
1/
18
1,
#940
0,
#950
0/
08
1,
#960
0,
#970
0$
1#
0(
b1000111 .
b1000111 2
b1000111 7
b10 0
b10 4
b1111 3
b1111 6
b1 5
1/
18
1,
#980
0,
#990
0/
08
1,
