problems/05_hex_counter/hex_display.v
module hex_display(
    input clk,
    input [15:0]data,

    output [3:0]anodes,
    output [6:0]segments
);

/*
*   Problem 3/7:
*   Write logic for dynamic indication here.
*/
//Solve:
reg [1:0]i = 0;

assign anodes = (4'b1 << i);

always @(posedge clk) begin
    i <= i + 2'b1;
end

wire [3:0]b = data[i * 4 +: 4];
hex_to_seg hex_to_seg(.data(b), .segments(segments));

endmodule

module hex_to_seg(
    input [3:0]data,

    output reg [6:0]segments
);

always @(*) begin
    case (data)          /* abcdefg */
        4'h0: segments = 7'b1111110;
        4'h1: segments = 7'b0110000;
        4'h2: segments = 7'b1101101;
        4'h3: segments = 7'b1111001;
        4'h4: segments = 7'b0110011;
        4'h5: segments = 7'b1011011;
        4'h6: segments = 7'b1011111;
        4'h7: segments = 7'b1110000;
        4'h8: segments = 7'b1111111;
        4'h9: segments = 7'b1111011;
        4'hA: segments = 7'b1110111;
        4'hB: segments = 7'b0011111;
        4'hC: segments = 7'b1001110;
        4'hD: segments = 7'b0111101;
        4'hE: segments = 7'b1001111;
        4'hF: segments = 7'b1000111;
    endcase
end

endmodule

problems/05_hex_counter/counter.v
module counter #(parameter W = 16)(
    input clk,

    output [W - 1:0]q
);
reg [W-1:0]cnt = 0;
assign q = cnt;
always @(posedge clk) begin
        cnt <= cnt + 1'b1;
end



/*
*   Write your code for counter of W bit width here
*/

endmodule

problems/05_hex_counter/clk_div.v
module clk_div #(parameter x = 1)(
    input clk,

    output clk_out
);

reg [x-1:0]cnt = 0;
assign clk_out = cnt[x-1];

always @ (posedge clk) begin
  cnt <= cnt + 1;
end
endmodule

problems/05_hex_counter/top.v
module top(
    input CLK,

    output DS_EN1, DS_EN2, DS_EN3, DS_EN4,
    output DS_A, DS_B, DS_C, DS_D, DS_E, DS_F, DS_G
);

wire [3:0]anodes;
assign {DS_EN1, DS_EN2, DS_EN3, DS_EN4} = ~anodes;

wire [6:0]segments;
assign {DS_A, DS_B, DS_C, DS_D, DS_E, DS_F, DS_G} = segments;

wire [15:0]data; /* Data bus */
wire clk1, clk2; /* Clocks */

/*
*   Instantiate hex display driver, 16-bit counter and two clock dividers here
*/
  clk_div #(.x(24)) div_for_counter(.clk(CLK),.clk_out(clk1));
  clk_div #(.x(16)) div_for_display(.clk(CLK),. clk_out(clk2));
  counter #(.W(16))data_gen(.clk(clk1),.q(data));
  hex_display display(.clk(clk2),.data(data),.anodes(anodes),.segments(segments));

endmodule

problems/05_hex_counter/testbench.v
`timescale 1 ns / 100 ps

/*
*   Introduction to FPGA and Verilog
*
*   Viktor Prutyanov, 2019
*
*   Testbench for problem set #05
*/

module testbench();
reg clk = 1'b0;

always begin
    #1 clk = ~clk;
end
top top(clk, DS_EN1, DS_EN2, DS_EN3, DS_EN4, DS_A, DS_B, DS_C, DS_D, DS_E, DS_F, DS_G);

initial begin
    $dumpvars;
    #100000 $finish;
end

endmodule

problems/05_hex_counter/dump.vcd
$date
	Tue Nov 12 19:52:10 2019
$end
$version
	Icarus Verilog
$end
$timescale
	100ps
$end
$scope module testbench $end
$var wire 1 ! DS_G $end
$var wire 1 " DS_F $end
$var wire 1 # DS_EN4 $end
$var wire 1 $ DS_EN3 $end
$var wire 1 % DS_EN2 $end
$var wire 1 & DS_EN1 $end
$var wire 1 ' DS_E $end
$var wire 1 ( DS_D $end
$var wire 1 ) DS_C $end
$var wire 1 * DS_B $end
$var wire 1 + DS_A $end
$var reg 1 , clk $end
$scope module top $end
$var wire 1 , CLK $end
$var wire 7 - segments [6:0] $end
$var wire 16 . data [15:0] $end
$var wire 1 / clk2 $end
$var wire 1 0 clk1 $end
$var wire 4 1 anodes [3:0] $end
$var wire 1 ! DS_G $end
$var wire 1 " DS_F $end
$var wire 1 # DS_EN4 $end
$var wire 1 $ DS_EN3 $end
$var wire 1 % DS_EN2 $end
$var wire 1 & DS_EN1 $end
$var wire 1 ' DS_E $end
$var wire 1 ( DS_D $end
$var wire 1 ) DS_C $end
$var wire 1 * DS_B $end
$var wire 1 + DS_A $end
$scope module data_gen $end
$var wire 16 2 q [15:0] $end
$var wire 1 0 clk $end
$var reg 16 3 cnt [15:0] $end
$upscope $end
$scope module display $end
$var wire 16 4 data [15:0] $end
$var wire 7 5 segments [6:0] $end
$var wire 1 / clk $end
$var wire 4 6 b [3:0] $end
$var wire 4 7 anodes [3:0] $end
$var reg 2 8 i [1:0] $end
$scope module hex_to_seg $end
$var wire 4 9 data [3:0] $end
$var reg 7 : segments [6:0] $end
$upscope $end
$upscope $end
$scope module div_for_counter $end
$var wire 1 , clk $end
$var wire 1 0 clk_out $end
$var reg 24 ; cnt [23:0] $end
$upscope $end
$scope module div_for_display $end
$var wire 1 , clk $end
$var wire 1 / clk_out $end
$var reg 16 < cnt [15:0] $end
$upscope $end
$upscope $end
$upscope $end
$enddefinitions $end
#0
$dumpvars
b0 <
b0 ;
b1111110 :
b0 9
b0 8
b1 7
b0 6
b1111110 5
b0 4
b0 3
b0 2
b1 1
00
0/
b0 .
b1111110 -
0,
1+
1*
1)
1(
1'
1&
1%
1$
0#
1"
0!
$end
#10
b1 ;
b1 <
1,
#20
0,
#30
b10 <
b10 ;
1,
#40
0,
#50
b11 ;
b11 <
1,
#60
0,
#70
b100 <
b100 ;
1,
#80
0,
#90
b101 ;
b101 <
1,
#100
0,
#110
b110 <
b110 ;
1,
#120
0,
#130
b111 ;
b111 <
1,
#140
0,
#150
b1000 <
b1000 ;
1,
#160
0,
#170
b1001 ;
b1001 <
1,
#180
0,
#190
b1010 <
b1010 ;
1,
#200
0,
#210
b1011 ;
b1011 <
1,
#220
0,
#230
b1100 <
b1100 ;
1,
#240
0,
#250
b1101 ;
b1101 <
1,
#260
0,
#270
b1110 <
b1110 ;
1,
#280
0,
#290
b1111 ;
b1111 <
1,
#300
0,
#310
b10000 <
b10000 ;
1,
#320
0,
#330
b10001 ;
b10001 <
1,
#340
0,
#350
b10010 <
b10010 ;
1,
#360
0,
#370
b10011 ;
b10011 <
1,
#380
0,
#390
b10100 <
b10100 ;
1,
#400
0,
#410
b10101 ;
b10101 <
1,
#420
0,
#430
b10110 <
b10110 ;
1,
#440
0,
#450
b10111 ;
b10111 <
1,
#460
0,
#470
b11000 <
b11000 ;
1,
#480
0,
#490
b11001 ;
b11001 <
1,
#500
0,
#510
b11010 <
b11010 ;
1,
#520
0,
#530
b11011 ;
b11011 <
1,
#540
0,
#550
b11100 <
b11100 ;
1,
#560
0,
#570
b11101 ;
b11101 <
1,
#580
0,
#590
b11110 <
b11110 ;
1,
#600
0,
#610
b11111 ;
b11111 <
1,
#620
0,
#630
b100000 <
b100000 ;
1,
#640
0,
#650
b100001 ;
b100001 <
1,
#660
0,
#670
b100010 <
b100010 ;
1,
#680
0,
#690
b100011 ;
b100011 <
1,
#700
0,
#710
b100100 <
b100100 ;
1,
#720
0,
#730
b100101 ;
b100101 <
1,
#740
0,
#750
b100110 <
b100110 ;
1,
#760
0,
#770
b100111 ;
b100111 <
1,
#780
0,
#790
b101000 <
b101000 ;
1,
#800
0,
#810
b101001 ;
b101001 <
1,
#820
0,
#830
b101010 <
b101010 ;
1,
#840
0,
#850
b101011 ;
b101011 <
1,
#860
0,
#870
b101100 <
b101100 ;
1,
#880
0,
#890
b101101 ;
b101101 <
1,
#900
0,
#910
b101110 <
b101110 ;
1,
#920
0,
#930
b101111 ;
b101111 <
1,
#940
0,
#950
b110000 <
b110000 ;
1,
#960
0,
#970
b110001 ;
b110001 <
1,
#980
0,
#990
b110010 <
b110010 ;
1,
#1000
0,
#1010
b110011 ;
b110011 <
1,
#1020
0,
#1030
b110100 <
b110100 ;
1,
#1040
0,
#1050
b110101 ;
b110101 <
1,
#1060
0,
#1070
b110110 <
b110110 ;
1,
#1080
0,
#1090
b110111 ;
b110111 <
1,
#1100
0,
#1110
b111000 <
b111000 ;
1,
#1120
0,
#1130
b111001 ;
b111001 <
1,
#1140
0,
#1150
b111010 <
b111010 ;
1,
#1160
0,
#1170
b111011 ;
b111011 <
1,
#1180
0,
#1190
b111100 <
b111100 ;
1,
#1200
0,
#1210
b111101 ;
b111101 <
1,
#1220
0,
#1230
b111110 <
b111110 ;
1,
#1240
0,
#1250
b111111 ;
b111111 <
1,
#1260
0,
#1270
b1000000 <
b1000000 ;
1,
#1280
0,
#1290
b1000001 ;
b1000001 <
1,
#1300
0,
#1310
b1000010 <
b1000010 ;
1,
#1320
0,
#1330
b1000011 ;
b1000011 <
1,
#1340
0,
#1350
b1000100 <
b1000100 ;
1,
#1360
0,
#1370
b1000101 ;
b1000101 <
1,
#1380
0,
#1390
b1000110 <
b1000110 ;
1,
#1400
0,
#1410
b1000111 ;
b1000111 <
1,
#1420
0,
#1430
b1001000 <
b1001000 ;
1,
#1440
0,
#1450
b1001001 ;
b1001001 <
1,
#1460
0,
#1470
b1001010 <
b1001010 ;
1,
#1480
0,
#1490
b1001011 ;
b1001011 <
1,
#1500
0,
#1510
b1001100 <
b1001100 ;
1,
#1520
0,
#1530
b1001101 ;
b1001101 <
1,
#1540
0,
#1550
b1001110 <
b1001110 ;
1,
#1560
0,
#1570
b1001111 ;
b1001111 <
1,
#1580
0,
#1590
b1010000 <
b1010000 ;
1,
#1600
0,
#1610
b1010001 ;
b1010001 <
1,
#1620
0,
#1630
b1010010 <
b1010010 ;
1,
#1640
0,
#1650
b1010011 ;
b1010011 <
1,
#1660
0,
#1670
b1010100 <
b1010100 ;
1,
#1680
0,
#1690
b1010101 ;
b1010101 <
1,
#1700
0,
#1710
b1010110 <
b1010110 ;
1,
#1720
0,
#1730
b1010111 ;
b1010111 <
1,
#1740
0,
#1750
b1011000 <
b1011000 ;
1,
#1760
0,
#1770
b1011001 ;
b1011001 <
1,
#1780
0,
#1790
b1011010 <
b1011010 ;
1,
#1800
0,
#1810
b1011011 ;
b1011011 <
1,
#1820
0,
#1830
b1011100 <
b1011100 ;
1,
#1840
0,
#1850
b1011101 ;
b1011101 <
1,
#1860
0,
#1870
b1011110 <
b1011110 ;
1,
#1880
0,
#1890
b1011111 ;
b1011111 <
1,
#1900
0,
#1910
b1100000 <
b1100000 ;
1,
#1920
0,
#1930
b1100001 ;
b1100001 <
1,
#1940
0,
#1950
b1100010 <
b1100010 ;
1,
#1960
0,
#1970
b1100011 ;
b1100011 <
1,
#1980
0,
#1990
b1100100 <
b1100100 ;
1,
#2000
0,
#2010
b1100101 ;
b1100101 <
1,
#2020
0,
#2030
b1100110 <
b1100110 ;
1,
#2040
0,
#2050
b1100111 ;
b1100111 <
1,
#2060
0,
#2070
b1101000 <
b1101000 ;
1,
#2080
0,
#2090
b1101001 ;
b1101001 <
1,
#2100
0,
#2110
b1101010 <
b1101010 ;
1,
#2120
0,
#2130
b1101011 ;
b1101011 <
1,
#2140
0,
#2150
b1101100 <
b1101100 ;
1,
#2160
0,
#2170
b1101101 ;
b1101101 <
1,
#2180
0,
#2190
b1101110 <
b1101110 ;
1,
#2200
0,
#2210
b1101111 ;
b1101111 <
1,
#2220
0,
#2230
b1110000 <
b1110000 ;
1,
#2240
0,
#2250
b1110001 ;
b1110001 <
1,
#2260
0,
#2270
b1110010 <
b1110010 ;
1,
#2280
0,
#2290
b1110011 ;
b1110011 <
1,
#2300
0,
#2310
b1110100 <
b1110100 ;
1,
#2320
0,
#2330
b1110101 ;
b1110101 <
1,
#2340
0,
#2350
b1110110 <
b1110110 ;
1,
#2360
0,
#2370
b1110111 ;
b1110111 <
1,
#2380
0,
#2390
b1111000 <
b1111000 ;
1,
#2400
0,
#2410
b1111001 ;
b1111001 <
1,
#2420
0,
#2430
b1111010 <
b1111010 ;
1,
#2440
0,
#2450
b1111011 ;
b1111011 <
1,
#2460
0,
#2470
b1111100 <
b1111100 ;
1,
#2480
0,
#2490
b1111101 ;
b1111101 <
1,
#2500
0,
#2510
b1111110 <
b1111110 ;
1,
#2520
0,
#2530
b1111111 ;
b1111111 <
1,
#2540
0,
#2550
b10000000 <
b10000000 ;
1,
#2560
0,
#2570
b10000001 ;
b10000001 <
1,
#2580
0,
#2590
b10000010 <
b10000010 ;
1,
#2600
0,
#2610
b10000011 ;
b10000011 <
1,
#2620
0,
#2630
b10000100 <
b10000100 ;
1,
#2640
0,
#2650
b10000101 ;
b10000101 <
1,
#2660
0,
#2670
b10000110 <
b10000110 ;
1,
#2680
0,
#2690
b10000111 ;
b10000111 <
1,
#2700
0,
#2710
b10001000 <
b10001000 ;
1,
#2720
0,
#2730
b10001001 ;
b10001001 <
1,
#2740
0,
#2750
b10001010 <
b10001010 ;
1,
#2760
0,
#2770
b10001011 ;
b10001011 <
1,
#2780
0,
#2790
b10001100 <
b10001100 ;
1,
#2800
0,
#2810
b10001101 ;
b10001101 <
1,
#2820
0,
#2830
b10001110 <
b10001110 ;
1,
#2840
0,
#2850
b10001111 ;
b10001111 <
1,
#2860
0,
#2870
b10010000 <
b10010000 ;
1,
#2880
0,
#2890
b10010001 ;
b10010001 <
1,
#2900
0,
#2910
b10010010 <
b10010010 ;
1,
#2920
0,
#2930
b10010011 ;
b10010011 <
1,
#2940
0,
#2950
b10010100 <
b10010100 ;
1,
#2960
0,
#2970
b10010101 ;
b10010101 <
1,
#2980
0,
#2990
b10010110 <
b10010110 ;
1,
#3000
0,
#3010
b10010111 ;
b10010111 <
1,
#3020
0,
#3030
b10011000 <
b10011000 ;
1,
#3040
0,
#3050
b10011001 ;
b10011001 <
1,
#3060
0,
#3070
b10011010 <
b10011010 ;
1,
#3080
0,
#3090
b10011011 ;
b10011011 <
1,
#3100
0,
#3110
b10011100 <
b10011100 ;
1,
#3120
0,
#3130
b10011101 ;
b10011101 <
1,
#3140
0,
#3150
b10011110 <
b10011110 ;
1,
#3160
0,
#3170
b10011111 ;
b10011111 <
1,
#3180
0,
#3190
b10100000 <
b10100000 ;
1,
#3200
0,
#3210
b10100001 ;
b10100001 <
1,
#3220
0,
#3230
b10100010 <
b10100010 ;
1,
#3240
0,
#3250
b10100011 ;
b10100011 <
1,
#3260
0,
#3270
b10100100 <
b10100100 ;
1,
#3280
0,
#3290
b10100101 ;
b10100101 <
1,
#3300
0,
#3310
b10100110 <
b10100110 ;
1,
#3320
0,
#3330
b10100111 ;
b10100111 <
1,
#3340
0,
#3350
b10101000 <
b10101000 ;
1,
#3360
0,
#3370
b10101001 ;
b10101001 <
1,
#3380
0,
#3390
b10101010 <
b10101010 ;
1,
#3400
0,
#3410
b10101011 ;
b10101011 <
1,
#3420
0,
#3430
b10101100 <
b10101100 ;
1,
#3440
0,
#3450
b10101101 ;
b10101101 <
1,
#3460
0,
#3470
b10101110 <
b10101110 ;
1,
#3480
0,
#3490
b10101111 ;
b10101111 <
1,
#3500
0,
#3510
b10110000 <
b10110000 ;
1,
#3520
0,
#3530
b10110001 ;
b10110001 <
1,
#3540
0,
#3550
b10110010 <
b10110010 ;
1,
#3560
0,
#3570
b10110011 ;
b10110011 <
1,
#3580
0,
#3590
b10110100 <
b10110100 ;
1,
#3600
0,
#3610
b10110101 ;
b10110101 <
1,
#3620
0,
#3630
b10110110 <
b10110110 ;
1,
#3640
0,
#3650
b10110111 ;
b10110111 <
1,
#3660
0,
#3670
b10111000 <
b10111000 ;
1,
#3680
0,
#3690
b10111001 ;
b10111001 <
1,
#3700
0,
#3710
b10111010 <
b10111010 ;
1,
#3720
0,
#3730
b10111011 ;
b10111011 <
1,
#3740
0,
#3750
b10111100 <
b10111100 ;
1,
#3760
0,
#3770
b10111101 ;
b10111101 <
1,
#3780
0,
#3790
b10111110 <
b10111110 ;
1,
#3800
0,
#3810
b10111111 ;
b10111111 <
1,
#3820
0,
#3830
b11000000 <
b11000000 ;
1,
#3840
0,
#3850
b11000001 ;
b11000001 <
1,
#3860
0,
#3870
b11000010 <
b11000010 ;
1,
#3880
0,
#3890
b11000011 ;
b11000011 <
1,
#3900
0,
#3910
b11000100 <
b11000100 ;
1,
#3920
0,
#3930
b11000101 ;
b11000101 <
1,
#3940
0,
#3950
b11000110 <
b11000110 ;
1,
#3960
0,
#3970
b11000111 ;
b11000111 <
1,
#3980
0,
#3990
b11001000 <
b11001000 ;
1,
#4000
0,
#4010
b11001001 ;
b11001001 <
1,
#4020
0,
#4030
b11001010 <
b11001010 ;
1,
#4040
0,
#4050
b11001011 ;
b11001011 <
1,
#4060
0,
#4070
b11001100 <
b11001100 ;
1,
#4080
0,
#4090
b11001101 ;
b11001101 <
1,
#4100
0,
#4110
b11001110 <
b11001110 ;
1,
#4120
0,
#4130
b11001111 ;
b11001111 <
1,
#4140
0,
#4150
b11010000 <
b11010000 ;
1,
#4160
0,
#4170
b11010001 ;
b11010001 <
1,
#4180
0,
#4190
b11010010 <
b11010010 ;
1,
#4200
0,
#4210
b11010011 ;
b11010011 <
1,
#4220
0,
#4230
b11010100 <
b11010100 ;
1,
#4240
0,
#4250
b11010101 ;
b11010101 <
1,
#4260
0,
#4270
b11010110 <
b11010110 ;
1,
#4280
0,
#4290
b11010111 ;
b11010111 <
1,
#4300
0,
#4310
b11011000 <
b11011000 ;
1,
#4320
0,
#4330
b11011001 ;
b11011001 <
1,
#4340
0,
#4350
b11011010 <
b11011010 ;
1,
#4360
0,
#4370
b11011011 ;
b11011011 <
1,
#4380
0,
#4390
b11011100 <
b11011100 ;
1,
#4400
0,
#4410
b11011101 ;
b11011101 <
1,
#4420
0,
#4430
b11011110 <
b11011110 ;
1,
#4440
0,
#4450
b11011111 ;
b11011111 <
1,
#4460
0,
#4470
b11100000 <
b11100000 ;
1,
#4480
0,
#4490
b11100001 ;
b11100001 <
1,
#4500
0,
#4510
b11100010 <
b11100010 ;
1,
#4520
0,
#4530
b11100011 ;
b11100011 <
1,
#4540
0,
#4550
b11100100 <
b11100100 ;
1,
#4560
0,
#4570
b11100101 ;
b11100101 <
1,
#4580
0,
#4590
b11100110 <
b11100110 ;
1,
#4600
0,
#4610
b11100111 ;
b11100111 <
1,
#4620
0,
#4630
b11101000 <
b11101000 ;
1,
#4640
0,
#4650
b11101001 ;
b11101001 <
1,
#4660
0,
#4670
b11101010 <
b11101010 ;
1,
#4680
0,
#4690
b11101011 ;
b11101011 <
1,
#4700
0,
#4710
b11101100 <
b11101100 ;
1,
#4720
0,
#4730
b11101101 ;
b11101101 <
1,
#4740
0,
#4750
b11101110 <
b11101110 ;
1,
#4760
0,
#4770
b11101111 ;
b11101111 <
1,
#4780
0,
#4790
b11110000 <
b11110000 ;
1,
#4800
0,
#4810
b11110001 ;
b11110001 <
1,
#4820
0,
#4830
b11110010 <
b11110010 ;
1,
#4840
0,
#4850
b11110011 ;
b11110011 <
1,
#4860
0,
#4870
b11110100 <
b11110100 ;
1,
#4880
0,
#4890
b11110101 ;
b11110101 <
1,
#4900
0,
#4910
b11110110 <
b11110110 ;
1,
#4920
0,
#4930
b11110111 ;
b11110111 <
1,
#4940
0,
#4950
b11111000 <
b11111000 ;
1,
#4960
0,
#4970
b11111001 ;
b11111001 <
1,
#4980
0,
#4990
b11111010 <
b11111010 ;
1,
#5000
0,
#5010
b11111011 ;
b11111011 <
1,
#5020
0,
#5030
b11111100 <
b11111100 ;
1,
#5040
0,
#5050
b11111101 ;
b11111101 <
1,
#5060
0,
#5070
b11111110 <
b11111110 ;
1,
#5080
0,
#5090
b11111111 ;
b11111111 <
1,
#5100
0,
#5110
b100000000 <
b100000000 ;
1,
#5120
0,
#5130
b100000001 ;
b100000001 <
1,
#5140
0,
#5150
b100000010 <
b100000010 ;
1,
#5160
0,
#5170
b100000011 ;
b100000011 <
1,
#5180
0,
#5190
b100000100 <
b100000100 ;
1,
#5200
0,
#5210
b100000101 ;
b100000101 <
1,
#5220
0,
#5230
b100000110 <
b100000110 ;
1,
#5240
0,
#5250
b100000111 ;
b100000111 <
1,
#5260
0,
#5270
b100001000 <
b100001000 ;
1,
#5280
0,
#5290
b100001001 ;
b100001001 <
1,
#5300
0,
#5310
b100001010 <
b100001010 ;
1,
#5320
0,
#5330
b100001011 ;
b100001011 <
1,
#5340
0,
#5350
b100001100 <
b100001100 ;
1,
#5360
0,
#5370
b100001101 ;
b100001101 <
1,
#5380
0,
#5390
b100001110 <
b100001110 ;
1,
#5400
0,
#5410
b100001111 ;
b100001111 <
1,
#5420
0,
#5430
b100010000 <
b100010000 ;
1,
#5440
0,
#5450
b100010001 ;
b100010001 <
1,
#5460
0,
#5470
b100010010 <
b100010010 ;
1,
#5480
0,
#5490
b100010011 ;
b100010011 <
1,
#5500
0,
#5510
b100010100 <
b100010100 ;
1,
#5520
0,
#5530
b100010101 ;
b100010101 <
1,
#5540
0,
#5550
b100010110 <
b100010110 ;
1,
#5560
0,
#5570
b100010111 ;
b100010111 <
1,
#5580
0,
#5590
b100011000 <
b100011000 ;
1,
#5600
0,
#5610
b100011001 ;
b100011001 <
1,
#5620
0,
#5630
b100011010 <
b100011010 ;
1,
#5640
0,
#5650
b100011011 ;
b100011011 <
1,
#5660
0,
#5670
b100011100 <
b100011100 ;
1,
#5680
0,
#5690
b100011101 ;
b100011101 <
1,
#5700
0,
#5710
b100011110 <
b100011110 ;
1,
#5720
0,
#5730
b100011111 ;
b100011111 <
1,
#5740
0,
#5750
b100100000 <
b100100000 ;
1,
#5760
0,
#5770
b100100001 ;
b100100001 <
1,
#5780
0,
#5790
b100100010 <
b100100010 ;
1,
#5800
0,
#5810
b100100011 ;
b100100011 <
1,
#5820
0,
#5830
b100100100 <
b100100100 ;
1,
#5840
0,
#5850
b100100101 ;
b100100101 <
1,
#5860
0,
#5870
b100100110 <
b100100110 ;
1,
#5880
0,
#5890
b100100111 ;
b100100111 <
1,
#5900
0,
#5910
b100101000 <
b100101000 ;
1,
#5920
0,
#5930
b100101001 ;
b100101001 <
1,
#5940
0,
#5950
b100101010 <
b100101010 ;
1,
#5960
0,
#5970
b100101011 ;
b100101011 <
1,
#5980
0,
#5990
b100101100 <
b100101100 ;
1,
#6000
0,
#6010
b100101101 ;
b100101101 <
1,
#6020
0,
#6030
b100101110 <
b100101110 ;
1,
#6040
0,
#6050
b100101111 ;
b100101111 <
1,
#6060
0,
#6070
b100110000 <
b100110000 ;
1,
#6080
0,
#6090
b100110001 ;
b100110001 <
1,
#6100
0,
#6110
b100110010 <
b100110010 ;
1,
#6120
0,
#6130
b100110011 ;
b100110011 <
1,
#6140
0,
#6150
b100110100 <
b100110100 ;
1,
#6160
0,
#6170
b100110101 ;
b100110101 <
1,
#6180
0,
#6190
b100110110 <
b100110110 ;
1,
#6200
0,
#6210
b100110111 ;
b100110111 <
1,
#6220
0,
#6230
b100111000 <
b100111000 ;
1,
#6240
0,
#6250
b100111001 ;
b100111001 <
1,
#6260
0,
#6270
b100111010 <
b100111010 ;
1,
#6280
0,
#6290
b100111011 ;
b100111011 <
1,
#6300
0,
#6310
b100111100 <
b100111100 ;
1,
#6320
0,
#6330
b100111101 ;
b100111101 <
1,
#6340
0,
#6350
b100111110 <
b100111110 ;
1,
#6360
0,
#6370
b100111111 ;
b100111111 <
1,
#6380
0,
#6390
b101000000 <
b101000000 ;
1,
#6400
0,
#6410
b101000001 ;
b101000001 <
1,
#6420
0,
#6430
b101000010 <
b101000010 ;
1,
#6440
0,
#6450
b101000011 ;
b101000011 <
1,
#6460
0,
#6470
b101000100 <
b101000100 ;
1,
#6480
0,
#6490
b101000101 ;
b101000101 <
1,
#6500
0,
#6510
b101000110 <
b101000110 ;
1,
#6520
0,
#6530
b101000111 ;
b101000111 <
1,
#6540
0,
#6550
b101001000 <
b101001000 ;
1,
#6560
0,
#6570
b101001001 ;
b101001001 <
1,
#6580
0,
#6590
b101001010 <
b101001010 ;
1,
#6600
0,
#6610
b101001011 ;
b101001011 <
1,
#6620
0,
#6630
b101001100 <
b101001100 ;
1,
#6640
0,
#6650
b101001101 ;
b101001101 <
1,
#6660
0,
#6670
b101001110 <
b101001110 ;
1,
#6680
0,
#6690
b101001111 ;
b101001111 <
1,
#6700
0,
#6710
b101010000 <
b101010000 ;
1,
#6720
0,
#6730
b101010001 ;
b101010001 <
1,
#6740
0,
#6750
b101010010 <
b101010010 ;
1,
#6760
0,
#6770
b101010011 ;
b101010011 <
1,
#6780
0,
#6790
b101010100 <
b101010100 ;
1,
#6800
0,
#6810
b101010101 ;
b101010101 <
1,
#6820
0,
#6830
b101010110 <
b101010110 ;
1,
#6840
0,
#6850
b101010111 ;
b101010111 <
1,
#6860
0,
#6870
b101011000 <
b101011000 ;
1,
#6880
0,
#6890
b101011001 ;
b101011001 <
1,
#6900
0,
#6910
b101011010 <
b101011010 ;
1,
#6920
0,
#6930
b101011011 ;
b101011011 <
1,
#6940
0,
#6950
b101011100 <
b101011100 ;
1,
#6960
0,
#6970
b101011101 ;
b101011101 <
1,
#6980
0,
#6990
b101011110 <
b101011110 ;
1,
#7000
0,
#7010
b101011111 ;
b101011111 <
1,
#7020
0,
#7030
b101100000 <
b101100000 ;
1,
#7040
0,
#7050
b101100001 ;
b101100001 <
1,
#7060
0,
#7070
b101100010 <
b101100010 ;
1,
#7080
0,
#7090
b101100011 ;
b101100011 <
1,
#7100
0,
#7110
b101100100 <
b101100100 ;
1,
#7120
0,
#7130
b101100101 ;
b101100101 <
1,
#7140
0,
#7150
b101100110 <
b101100110 ;
1,
#7160
0,
#7170
b101100111 ;
b101100111 <
1,
#7180
0,
#7190
b101101000 <
b101101000 ;
1,
#7200
0,
#7210
b101101001 ;
b101101001 <
1,
#7220
0,
#7230
b101101010 <
b101101010 ;
1,
#7240
0,
#7250
b101101011 ;
b101101011 <
1,
#7260
0,
#7270
b101101100 <
b101101100 ;
1,
#7280
0,
#7290
b101101101 ;
b101101101 <
1,
#7300
0,
#7310
b101101110 <
b101101110 ;
1,
#7320
0,
#7330
b101101111 ;
b101101111 <
1,
#7340
0,
#7350
b101110000 <
b101110000 ;
1,
#7360
0,
#7370
b101110001 ;
b101110001 <
1,
#7380
0,
#7390
b101110010 <
b101110010 ;
1,
#7400
0,
#7410
b101110011 ;
b101110011 <
1,
#7420
0,
#7430
b101110100 <
b101110100 ;
1,
#7440
0,
#7450
b101110101 ;
b101110101 <
1,
#7460
0,
#7470
b101110110 <
b101110110 ;
1,
#7480
0,
#7490
b101110111 ;
b101110111 <
1,
#7500
0,
#7510
b101111000 <
b101111000 ;
1,
#7520
0,
#7530
b101111001 ;
b101111001 <
1,
#7540
0,
#7550
b101111010 <
b101111010 ;
1,
#7560
0,
#7570
b101111011 ;
b101111011 <
1,
#7580
0,
#7590
b101111100 <
b101111100 ;
1,
#7600
0,
#7610
b101111101 ;
b101111101 <
1,
#7620
0,
#7630
b101111110 <
b101111110 ;
1,
#7640
0,
#7650
b101111111 ;
b101111111 <
1,
#7660
0,
#7670
b110000000 <
b110000000 ;
1,
#7680
0,
#7690
b110000001 ;
b110000001 <
1,
#7700
0,
#7710
b110000010 <
b110000010 ;
1,
#7720
0,
#7730
b110000011 ;
b110000011 <
1,
#7740
0,
#7750
b110000100 <
b110000100 ;
1,
#7760
0,
#7770
b110000101 ;
b110000101 <
1,
#7780
0,
#7790
b110000110 <
b110000110 ;
1,
#7800
0,
#7810
b110000111 ;
b110000111 <
1,
#7820
0,
#7830
b110001000 <
b110001000 ;
1,
#7840
0,
#7850
b110001001 ;
b110001001 <
1,
#7860
0,
#7870
b110001010 <
b110001010 ;
1,
#7880
0,
#7890
b110001011 ;
b110001011 <
1,
#7900
0,
#7910
b110001100 <
b110001100 ;
1,
#7920
0,
#7930
b110001101 ;
b110001101 <
1,
#7940
0,
#7950
b110001110 <
b110001110 ;
1,
#7960
0,
#7970
b110001111 ;
b110001111 <
1,
#7980
0,
#7990
b110010000 <
b110010000 ;
1,
#8000
0,
#8010
b110010001 ;
b110010001 <
1,
#8020
0,
#8030
b110010010 <
b110010010 ;
1,
#8040
0,
#8050
b110010011 ;
b110010011 <
1,
#8060
0,
#8070
b110010100 <
b110010100 ;
1,
#8080
0,
#8090
b110010101 ;
b110010101 <
1,
#8100
0,
#8110
b110010110 <
b110010110 ;
1,
#8120
0,
#8130
b110010111 ;
b110010111 <
1,
#8140
0,
#8150
b110011000 <
b110011000 ;
1,
#8160
0,
#8170
b110011001 ;
b110011001 <
1,
#8180
0,
#8190
b110011010 <
b110011010 ;
1,
#8200
0,
#8210
b110011011 ;
b110011011 <
1,
#8220
0,
#8230
b110011100 <
b110011100 ;
1,
#8240
0,
#8250
b110011101 ;
b110011101 <
1,
#8260
0,
#8270
b110011110 <
b110011110 ;
1,
#8280
0,
#8290
b110011111 ;
b110011111 <
1,
#8300
0,
#8310
b110100000 <
b110100000 ;
1,
#8320
0,
#8330
b110100001 ;
b110100001 <
1,
#8340
0,
#8350
b110100010 <
b110100010 ;
1,
#8360
0,
#8370
b110100011 ;
b110100011 <
1,
#8380
0,
#8390
b110100100 <
b110100100 ;
1,
#8400
0,
#8410
b110100101 ;
b110100101 <
1,
#8420
0,
#8430
b110100110 <
b110100110 ;
1,
#8440
0,
#8450
b110100111 ;
b110100111 <
1,
#8460
0,
#8470
b110101000 <
b110101000 ;
1,
#8480
0,
#8490
b110101001 ;
b110101001 <
1,
#8500
0,
#8510
b110101010 <
b110101010 ;
1,
#8520
0,
#8530
b110101011 ;
b110101011 <
1,
#8540
0,
#8550
b110101100 <
b110101100 ;
1,
#8560
0,
#8570
b110101101 ;
b110101101 <
1,
#8580
0,
#8590
b110101110 <
b110101110 ;
1,
#8600
0,
#8610
b110101111 ;
b110101111 <
1,
#8620
0,
#8630
b110110000 <
b110110000 ;
1,
#8640
0,
#8650
b110110001 ;
b110110001 <
1,
#8660
0,
#8670
b110110010 <
b110110010 ;
1,
#8680
0,
#8690
b110110011 ;
b110110011 <
1,
#8700
0,
#8710
b110110100 <
b110110100 ;
1,
#8720
0,
